{
  "name": "DependencyInjection",
  "homepage": "https://github.com/Soulskater/DependencyInjection",
  "authors": [
    "Soulskater <gmeszaros007@gmail.com>"
  ],
  "description": "Super lightweight object oriented javascript with dependency injection",
  "keywords": [
    "dependency",
    "injection",
    "oop",
    "javascript",
    "di",
    "inheritance"
  ],
  "license": "MIT",
  "ignore": [
    "**/.*",
    "node_modules",
    "bower_components",
    "packages",
    "test",
    "tests"
  ],
  "_release": "4f7b8591ac",
  "_resolution": {
    "type": "branch",
    "branch": "master",
    "commit": "4f7b8591ac8581bd6b4df8c300c416f7ac82430c"
  },
  "_source": "git://github.com/Soulskater/DependencyInjection.git",
  "_target": "*",
  "_originalSource": "dependency-injection"
}